odoo/addons/fieldservice_stock_account/README.rst
odoo/addons/fieldservice_stock_account/__init__.py
odoo/addons/fieldservice_stock_account/__manifest__.py
odoo/addons/fieldservice_stock_account/i18n/de.po
odoo/addons/fieldservice_stock_account/i18n/es.po
odoo/addons/fieldservice_stock_account/i18n/es_AR.po
odoo/addons/fieldservice_stock_account/i18n/es_CL.po
odoo/addons/fieldservice_stock_account/i18n/fieldservice_stock_account.pot
odoo/addons/fieldservice_stock_account/i18n/it.po
odoo/addons/fieldservice_stock_account/i18n/pt_BR.po
odoo/addons/fieldservice_stock_account/models/__init__.py
odoo/addons/fieldservice_stock_account/models/fsm_order.py
odoo/addons/fieldservice_stock_account/readme/CONTRIBUTORS.rst
odoo/addons/fieldservice_stock_account/readme/CREDITS.rst
odoo/addons/fieldservice_stock_account/readme/DESCRIPTION.rst
odoo/addons/fieldservice_stock_account/readme/USAGE.rst
odoo/addons/fieldservice_stock_account/static/description/icon.png
odoo/addons/fieldservice_stock_account/static/description/index.html
odoo/addons/fieldservice_stock_account/tests/__init__.py
odoo/addons/fieldservice_stock_account/tests/test_fsm_stock_account.py
odoo14_addon_fieldservice_stock_account-14.0.1.0.1.dist-info/METADATA
odoo14_addon_fieldservice_stock_account-14.0.1.0.1.dist-info/WHEEL
odoo14_addon_fieldservice_stock_account-14.0.1.0.1.dist-info/top_level.txt
odoo14_addon_fieldservice_stock_account-14.0.1.0.1.dist-info/RECORD
