Metadata-Version: 2.1
Name: odoo14-addon-fieldservice_stock_account
Version: 14.0.1.0.1
Summary: Invoice inventory items delivered with Field Service orders
Home-page: https://github.com/OCA/field-service
Author: Open Source Integrators, Odoo Community Association (OCA)
Author-email: support@odoo-community.org
License: AGPL-3
Classifier: Programming Language :: Python
Classifier: Framework :: Odoo
Classifier: Framework :: Odoo :: 14.0
Classifier: License :: OSI Approved :: GNU Affero General Public License v3
Classifier: Development Status :: 4 - Beta
Requires-Python: >=3.6
Requires-Dist: odoo14-addon-account-invoice-report-hide-line
Requires-Dist: odoo14-addon-fieldservice-account
Requires-Dist: odoo14-addon-fieldservice-stock-request
Requires-Dist: odoo<14.1dev,>=14.0a
